[
  {
    "name": "11.1 Key Points: (In Progress)",
    "tags": ["11.1"], 
    "guideLink": "",
    "practiceLinks": [
      {
        "name": "",
        "link": ""
      }
      
      
    ],
    "extraHelpLinks": [
      {
        "name": "",
        "link": ""
      }
    ]
  },
  {
    "name": "11.2 Key Points: (In Progress)",
    "tags": ["11.2"], 
    "guideLink": "",
    "practiceLinks": [
      {
        "name": "",
        "link": ""
      }
    
    ],
    "extraHelpLinks": [
      {
        "name": "",
        "link": ""
      }
    ]
  },
  {
    "name": "11.3 Key Points: (In Progress)",
    "tags": ["11.3"], 
    "guideLink": "",
    "practiceLinks": [
      {
        "name": "",
        "link": ""
      }
      
    ],
    "extraHelpLinks": [
      {
        "name": "",
        "link": ""
      }
    ]
  }
]
