[
  {
    "name": "12.1 Key Points: (In Progress)",
    "tags": ["12.1"], 
    "guideLink": "",
    "practiceLinks": [
      {
        "name": "",
        "link": ""
      }
      
      
    ],
    "extraHelpLinks": [
      {
        "name": "",
        "link": ""
      }
    ]
  },
  {
    "name": "12.2 Key Points: (In Progress)",
    "tags": ["12.2"], 
    "guideLink": "",
    "practiceLinks": [
      {
        "name": "",
        "link": ""
      }
    
    ],
    "extraHelpLinks": [
      {
        "name": "",
        "link": ""
      }
    ]
  },
  {
    "name": "12.3 Key Points: (In Progress)",
    "tags": ["12.3"], 
    "guideLink": "",
    "practiceLinks": [
      {
        "name": "",
        "link": ""
      }
      
    ],
    "extraHelpLinks": [
      {
        "name": "",
        "link": ""
      }
    ]
  }
]
